pymlab/__init__.py
pymlab/main.py
pymlab/test.py
pymlab/train.py
pymlab/utils.py
mlab_py-1.0.15.dist-info/METADATA
mlab_py-1.0.15.dist-info/WHEEL
mlab_py-1.0.15.dist-info/RECORD
