Metadata-Version: 2.1
Name: mlab.py
Version: 1.0.15
Summary: Python packages for mlab ecosystem
Author: Kelvin Nketia-Achiampong
Author-email: disal.bot@gmlcv.onmicrosoft.com
Requires-Python: >=3.8,<4.0
Classifier: Programming Language :: Python :: 3
Classifier: Programming Language :: Python :: 3.8
Classifier: Programming Language :: Python :: 3.9
Classifier: Programming Language :: Python :: 3.10
Classifier: Programming Language :: Python :: 3.11
Classifier: Programming Language :: Python :: 3.12
